<?xml version="1.0" encoding="UTF-8"?>
<files psalm-version="5.26.1@d747f6500b38ac4f7dfc5edbcae6e4b637d7add0">
  <file src="src/Bridge/Symfony/Form/Type/HierarchyJsonType.php">
    <MoreSpecificImplementedParamType>
      <code><![CDATA[$options]]></code>
    </MoreSpecificImplementedParamType>
    <RedundantCondition>
      <code><![CDATA[null !== $type->propertyAccessor->getValue($data, self::ADMIN1_FIELD)]]></code>
      <code><![CDATA[null !== $type->propertyAccessor->getValue($data, self::ADMIN1_FIELD)]]></code>
      <code><![CDATA[null !== $type->propertyAccessor->getValue($data, self::ADMIN2_FIELD)]]></code>
    </RedundantCondition>
    <ReservedWord>
      <code><![CDATA[$event->getData()]]></code>
      <code><![CDATA[$type->propertyAccessor->getValue($data, self::ADMIN1_FIELD)]]></code>
    </ReservedWord>
  </file>
  <file src="src/Command/BuildCommand.php">
    <NonInvariantDocblockPropertyType>
      <code><![CDATA[$defaultName]]></code>
    </NonInvariantDocblockPropertyType>
    <PossiblyNullArgument>
      <code><![CDATA[$fileName]]></code>
    </PossiblyNullArgument>
    <PropertyNotSetInConstructor>
      <code><![CDATA[$ioWriter]]></code>
    </PropertyNotSetInConstructor>
    <UndefinedClass>
      <code><![CDATA[$node]]></code>
      <code><![CDATA[$node]]></code>
      <code><![CDATA[Crawler]]></code>
      <code><![CDATA[Crawler]]></code>
      <code><![CDATA[Crawler]]></code>
      <code><![CDATA[ProgressBar]]></code>
      <code><![CDATA[ProgressBar]]></code>
    </UndefinedClass>
    <UndefinedInterfaceMethod>
      <code><![CDATA[section]]></code>
    </UndefinedInterfaceMethod>
  </file>
  <file src="src/Exception/BuildException.php">
    <MissingParamType>
      <code><![CDATA[$code]]></code>
      <code><![CDATA[$message]]></code>
    </MissingParamType>
  </file>
  <file src="src/Parser.php">
    <ReservedWord>
      <code><![CDATA[$encoder->decode($unzippedCountry, CsvEncoder::FORMAT)]]></code>
    </ReservedWord>
  </file>
  <file src="tests/Bridge/Symfony/Form/Type/HierarchyJsonTypeTest.php">
    <InvalidArgument>
      <code><![CDATA[$values]]></code>
      <code><![CDATA[$values]]></code>
    </InvalidArgument>
  </file>
  <file src="tests/Exception/BuildExceptionTest.php">
    <UndefinedClass>
      <code><![CDATA[never]]></code>
    </UndefinedClass>
  </file>
</files>
